{"changes":{"crates/vespertide-macro/Cargo.toml":"Patch","crates/vespertide-config/Cargo.toml":"Patch","crates/vespertide-planner/Cargo.toml":"Patch","crates/vespertide-query/Cargo.toml":"Patch","crates/vespertide-loader/Cargo.toml":"Patch","crates/vespertide/Cargo.toml":"Patch","crates/vespertide-naming/Cargo.toml":"Patch","crates/vespertide-cli/Cargo.toml":"Patch","crates/vespertide-core/Cargo.toml":"Patch","crates/vespertide-exporter/Cargo.toml":"Patch"},"note":"Implement jpa","date":"2026-03-24T10:44:57.164009900Z"}